sklearn_ensemble_cv/__about__.py
sklearn_ensemble_cv/__init__.py
sklearn_ensemble_cv/cross_validation.py
sklearn_ensemble_cv/ensemble.py
sklearn_ensemble_cv/simu_data.py
sklearn_ensemble_cv/utils.py
sklearn_ensemble_cv-0.2.5.dist-info/METADATA
sklearn_ensemble_cv-0.2.5.dist-info/WHEEL
sklearn_ensemble_cv-0.2.5.dist-info/licenses/LICENSE
sklearn_ensemble_cv-0.2.5.dist-info/RECORD
