Metadata-Version: 2.4
Name: sklearn_ensemble_cv
Version: 0.2.5
Summary: Ensemble Cross-validation is a Python package for performing specialized cross-validation on ensemble models, such as extrapolated cross-validation (ECV), generalized cross-validation (GCV), and etc. The implementation of ensemble models are based on scikit-learn.
Author-email: Jin-Hong Du <jinhongd@andrew.cmu.com>
Maintainer-email: Jin-Hong Du <jinhongd@andrew.cmu.com>
License: MIT License
License-File: LICENSE
Classifier: Intended Audience :: Developers
Classifier: License :: OSI Approved :: MIT License
Classifier: Programming Language :: Python :: 3
Requires-Python: >=3.6
Requires-Dist: joblib
Requires-Dist: numba
Requires-Dist: numpy
Requires-Dist: pandas
Requires-Dist: pip
Requires-Dist: scikit-learn
Requires-Dist: tqdm
